transaction_middleware/__init__.py
transaction_middleware/functions.py
transaction_middleware/logging.py
transaction_middleware/settings.py
transaction_middleware/transaction_middleware.py
transaction_middleware-0.1.7.dist-info/LICENSE
transaction_middleware-0.1.7.dist-info/METADATA
transaction_middleware-0.1.7.dist-info/WHEEL
transaction_middleware-0.1.7.dist-info/RECORD
