Metadata-Version: 2.1
Name: transaction-middleware
Version: 0.1.7
Summary: Async Transaction Middleware for FastAPI/Starlette
Home-page: https://impalah.github.io/transaction-middleware/
License: MIT
Keywords: transaction,middleware,fastapi,starlette
Author: impalah
Author-email: impalah@gmail.com
Requires-Python: >=3.10
Classifier: Development Status :: 4 - Beta
Classifier: Framework :: FastAPI
Classifier: Intended Audience :: Developers
Classifier: License :: OSI Approved :: MIT License
Classifier: Programming Language :: Python :: 3
Classifier: Programming Language :: Python :: 3.10
Classifier: Programming Language :: Python :: 3.11
Classifier: Programming Language :: Python :: 3.12
Classifier: Topic :: Internet :: WWW/HTTP :: HTTP Servers
Classifier: Topic :: Internet :: WWW/HTTP :: Session
Classifier: Topic :: Software Development :: Libraries :: Python Modules
Requires-Dist: fastapi (>=0.105.0)
Requires-Dist: loguru (>=0.7.2)
Requires-Dist: pydantic[email] (>=2.5.3)
Requires-Dist: python-dotenv (>=1.0.0,<2.0.0)
Requires-Dist: svix-ksuid (>=0.6.2)
Project-URL: Documentation, https://impalah.github.io/transaction-middleware/
Project-URL: Repository, https://github.com/impalah/transaction-middleware
Project-URL: Source, https://github.com/impalah/transaction-middleware
